<?xml version='1.0' encoding='UTF-8'?>
<content>
<N3 id="001">
<num>N3-001</num>
<class> 碩博一                         </class>
<group></group>
<name> 專題討論（二） </name>
<teacher> 吳文中   ,  邱繼正* </teacher>
<score> 0 </score>
<time> [5]7~8  </time>
<must> 必修 </must>
<type> 講義 </type>
<place> 化工系館                      93406 </place>
<note></note>
</N3>

<N3 id="002">
<num>N3-002</num>
<class> 碩博二                         </class>
<group></group>
<name> 專題討論（四） </name>
<teacher> 吳　煒   ,  林家裕* </teacher>
<score> 0 </score>
<time> [5]7~8  </time>
<must> 必修 </must>
<type> 講義 </type>
<place> 化工系館                      93456 </place>
<note></note>
</N3>

<N3 id="003">
<num>N3-003</num>
<class> 碩博                           </class>
<group></group>
<name> 專題討論 </name>
<teacher> 黃定加   ,  吳文中* </teacher>
<score> 0 </score>
<time> [5]7~8  </time>
<must> 必修 </must>
<type> 講義 </type>
<place> 化工系館                      華立廳 </place>
<note> 碩三博三以上必修                                                         </note>
</N3>

<N3 id="013">
<num>N3-013</num>
<class> 碩博                           </class>
<group></group>
<name> 高等輸送現象 </name>
<teacher> 魏憲鴻  </teacher>
<score> 3 </score>
<time> [3]3~4  ,  [4]2  </time>
<must> 選修 </must>
<type> 講義 </type>
<place> 化工系館                      93406 </place>
<note> 碩一甲組生必選英語授課                                                   </note>
</N3>

<N3 id="014">
<num>N3-014</num>
<class> 碩博                           </class>
<group></group>
<name> 高等輸送現象 </name>
<teacher> 黃世宏  </teacher>
<score> 3 </score>
<time> [2]3~4  ,  [5]1  </time>
<must> 選修 </must>
<type> 講義 </type>
<place> 化工系館                      93806 </place>
<note> 碩一甲組生必選中文授課                                                   </note>
</N3>

<N3 id="016">
<num>N3-016</num>
<class> 碩博                           </class>
<group></group>
<name> 高分子構造、性質與應用 </name>
<teacher> 郭人鳳  </teacher>
<score> 3 </score>
<time> [3]2  ,  [4]3~4  </time>
<must> 選修 </must>
<type> 講義 </type>
<place> 化工系館                      93706 </place>
<note></note>
</N3>

<N3 id="024">
<num>N3-024</num>
<class> 碩博                           </class>
<group></group>
<name> 觸媒之發展及應用 </name>
<teacher> 林裕川*  ,  翁鴻山  </teacher>
<score> 3 </score>
<time> [4]7~8  ,  [2]2  </time>
<must> 選修 </must>
<type> 講義 </type>
<place> 化工系館                      93352 </place>
<note></note>
</N3>

<N3 id="111">
<num>N3-111</num>
<class> 碩博                           </class>
<group></group>
<name> 奈米材料與合成科技 </name>
<teacher> 鍾賢龍  </teacher>
<score> 3 </score>
<time> [2]5~7  </time>
<must> 選修 </must>
<type> 講義 </type>
<place> 化工系館                      93406 </place>
<note> 英語授課                                                                 </note>
</N3>

<N3 id="115">
<num>N3-115</num>
<class> 碩博                           </class>
<group></group>
<name> 化學工廠技術與管理實務（二） </name>
<teacher> 曾建臻  </teacher>
<score> 3 </score>
<time> [3]6~8  </time>
<must> 選修 </must>
<type> 講義 </type>
<place> 化工系館                      93420 </place>
<note></note>
</N3>

<N3 id="116">
<num>N3-116</num>
<class> 碩博                           </class>
<group></group>
<name> 生物材料特論 </name>
<teacher> 林睿哲   ,  詹正雄   ,  陳美瑾* </teacher>
<score> 3 </score>
<time> [1]5~6  ,  [5]2  </time>
<must> 選修 </must>
<type> 講義 </type>
<place> 化工系館                      93706 </place>
<note></note>
</N3>

<N3 id="118">
<num>N3-118</num>
<class> 碩博                           </class>
<group></group>
<name> 界面活性劑原理與應用 </name>
<teacher> 張鑑祥   ,  陳炳宏   ,  郭炳林* </teacher>
<score> 3 </score>
<time> [2]8~9  ,  [4]9  </time>
<must> 選修 </must>
<type> 講義 </type>
<place> 化工系館                      93420 </place>
<note></note>
</N3>

<N3 id="121">
<num>N3-121</num>
<class> 碩博                           </class>
<group></group>
<name> 高等化工製程分析 </name>
<teacher> 李谷彥  </teacher>
<score> 3 </score>
<time> [4]6~8  </time>
<must> 選修 </must>
<type> 講義 </type>
<place> 化工系館                      93406 </place>
<note> 需自備筆電並攜至上課教室使用                                             </note>
</N3>

<N3 id="122">
<num>N3-122</num>
<class> 碩博                           </class>
<group></group>
<name> 成核現象 </name>
<teacher> 陳進成  </teacher>
<score> 3 </score>
<time> [1]7~8  ,  [3]1  </time>
<must> 選修 </must>
<type> 講義 </type>
<place> 化工系館                      93422 </place>
<note></note>
</N3>

<N3 id="123">
<num>N3-123</num>
<class> 碩博                           </class>
<group></group>
<name> 化學工程（二） </name>
<teacher> 吳文中   ,  吳意珣* </teacher>
<score> 3 </score>
<time> [1]2~3  ,  [4]2  </time>
<must> 選修 </must>
<type> 講義 </type>
<place> 化工系館                      93806 </place>
<note> 限104學年度(含)以後入學之碩士班乙組生或博士生符合畢業資格規定第6條者選修 </note>
</N3>

<N3 id="155">
<num>N3-155</num>
<class> 碩博                           </class>
<group></group>
<name> 創意與創新於奈米科技 </name>
<teacher> 洪昭南  </teacher>
<score> 3 </score>
<time> [2]N~6  </time>
<must> 選修 </must>
<type> 講義 </type>
<place> 化工系館                      93352 </place>
<note></note>
</N3>

<N3 id="156">
<num>N3-156</num>
<class> 碩博                           </class>
<group></group>
<name> 程序模擬應用 </name>
<teacher> 吳　煒  </teacher>
<score> 3 </score>
<time> [2]5~7  </time>
<must> 選修 </must>
<type> 講義 </type>
<place> 化工系館                      93806 </place>
<note></note>
</N3>

<N3 id="157">
<num>N3-157</num>
<class> 碩博                           </class>
<group></group>
<name> 分子模擬 </name>
<teacher> 邱繼正  </teacher>
<score> 3 </score>
<time> [1]6  ,  [5]3~4  </time>
<must> 選修 </must>
<type> 講義 </type>
<place> 化工系館                      93352 </place>
<note></note>
</N3>

<N3 id="158">
<num>N3-158</num>
<class> 碩博                           </class>
<group></group>
<name> 鋰電池製作及應用 </name>
<teacher> 楊宏澤   ,  楊明長   ,  郭炳林*  ,  陳偉聖   ,  方冠榮   ,  林士剛  </teacher>
<score> 3 </score>
<time> [4]6~8  </time>
<must> 選修 </must>
<type> 講義 </type>
<place> 化工系館                      93706 </place>
<note></note>
</N3>

<N3 id="159">
<num>N3-159</num>
<class> 碩博                           </class>
<group></group>
<name> 製程最適化 </name>
<teacher> 張珏庭  </teacher>
<score> 3 </score>
<time> [2]8  ,  [3]7~8  </time>
<must> 選修 </must>
<type> 講義 </type>
<place> 化工系館                      93806 </place>
<note> 英語授課                                                                 </note>
</N3>

<N3 id="160">
<num>N3-160</num>
<class> 碩博                           </class>
<group></group>
<name> 高等高分子化學 </name>
<teacher> 陳　雲  </teacher>
<score> 3 </score>
<time> [2]7~9  </time>
<must> 選修 </must>
<type> 講義 </type>
<place> 化工系館                      93422 </place>
<note></note>
</N3>

</content>
