<?xml version='1.0' encoding='UTF-8'?>
<content>
<NC id="001">
<num>NC-001</num>
<class> 碩博                           </class>
<group></group>
<name> 專題討論（一） </name>
<teacher> 陳佳琳  </teacher>
<score> 1 </score>
<time> [2]5~6  </time>
<must> 必修 </must>
<type> 講義 </type>
<place> 水利系館                      4644 </place>
<note> 水利所與自災所合開，自災所學生及水利所外籍生優先選課 </note>
</NC>

<NC id="002">
<num>NC-002</num>
<class> 碩博                           </class>
<group></group>
<name> 專題討論（三） </name>
<teacher> 陳佳琳  </teacher>
<score> 1 </score>
<time> [2]5~6  </time>
<must> 必修 </must>
<type> 講義 </type>
<place> 水利系館                      4644 </place>
<note> 水利所與自災所合開，自災所學生及水利所外籍生優先選課 </note>
</NC>

<NC id="003">
<num>NC-003</num>
<class> 碩博                           </class>
<group></group>
<name> 防災概論 </name>
<teacher> 蔡光榮  </teacher>
<score> 3 </score>
<time> [5]3~N  </time>
<must> 必修 </must>
<type> 講義 </type>
<place> 水利系館                      4644 </place>
<note></note>
</NC>

<NC id="004">
<num>NC-004</num>
<class> 碩博                           </class>
<group></group>
<name> 水文系統模擬與預測 </name>
<teacher> 楊道昌   ,  郭振民   ,  游保杉* </teacher>
<score> 3 </score>
<time> [2]2~4  </time>
<must> 選修 </must>
<type> 講義 </type>
<place> 水利系館                      4646 </place>
<note> 水利所與自災所合開 </note>
</NC>

<NC id="005">
<num>NC-005</num>
<class> 碩一二                         </class>
<group></group>
<name> 天然災害經濟分析 </name>
<teacher> 郭彥廉  </teacher>
<score> 3 </score>
<time> [4]5~7  </time>
<must> 選修 </must>
<type> 講義 </type>
<place> 社科院大樓                    階梯教室-經濟 </place>
<note> 經濟分析工具領域--大學部三年級以上才能修習  (英語授課) </note>
</NC>

<NC id="006">
<num>NC-006</num>
<class> 碩博                           </class>
<group></group>
<name> 土石流災害防救實務 </name>
<teacher> 陳俞旭   ,  陳振宇   ,  蔡元融* </teacher>
<score> 3 </score>
<time> [3]2~4  </time>
<must> 選修 </must>
<type> 講義 </type>
<place> 水利系館                      4644 </place>
<note> 水利所與自災所合開 </note>
</NC>

<NC id="007">
<num>NC-007</num>
<class> 碩博                           </class>
<group></group>
<name> 中等水力學 </name>
<teacher> 陳佳琳*  ,  賴泉基  </teacher>
<score> 3 </score>
<time> [1]6~8  </time>
<must> 選修 </must>
<type> 講義 </type>
<place> 水利系館                      4650 </place>
<note> 水利所與自災所合開 </note>
</NC>

<NC id="008">
<num>NC-008</num>
<class> 碩博                           </class>
<group></group>
<name> 海岸管理學 </name>
<teacher> 陳璋玲  </teacher>
<score> 3 </score>
<time> [1]2~4  </time>
<must> 選修 </must>
<type> 講義 </type>
<place> 水利系館                      4644 </place>
<note></note>
</NC>

</content>
