<?xml version='1.0' encoding='UTF-8'?>
<content>
<P4 id="002">
<num>P4-002</num>
<class> 碩博一                         </class>
<group></group>
<name> 專題討論（二） </name>
<teacher> 呂宗行*  ,  王振源   ,  景鴻鑫   ,  譚俊豪   ,  賴維祥  </teacher>
<score> 1 </score>
<time day1="5" s1="6" e1="7"> [5]6~7  </time>
<must> 必修 </must>
<type> 研討 </type>
<place> 航太系館                      繼昌講堂 </place>
<note> 碩博一必修 </note>
</P4>

<P4 id="003">
<num>P4-003</num>
<class> 碩博二                         </class>
<group></group>
<name> 專題討論（四） </name>
<teacher> 呂宗行   ,  王振源   ,  景鴻鑫   ,  譚俊豪*  ,  賴維祥  </teacher>
<score> 1 </score>
<time day1="5" s1="6" e1="7"> [5]6~7  </time>
<must> 必修 </must>
<type> 研討 </type>
<place> 航太系館                      繼昌講堂 </place>
<note> 碩博二必修 </note>
</P4>

<P4 id="004">
<num>P4-004</num>
<class> 碩博三延                       </class>
<group></group>
<name> 專題討論 </name>
<teacher> 呂宗行   ,  王振源   ,  景鴻鑫   ,  譚俊豪   ,  賴維祥* </teacher>
<score> 0 </score>
<time day1="5" s1="6" e1="7"> [5]6~7  </time>
<must> 必修 </must>
<type> 研討 </type>
<place> 航太系館                      繼昌講堂 </place>
<note></note>
</P4>

<P4 id="005">
<num>P4-005</num>
<class> 碩博                           </class>
<group></group>
<name> 航太工程計畫管理 </name>
<teacher> 祝飛鴻  </teacher>
<score> 3 </score>
<time day1="2" s1="5" e1="7"> [2]5~7  </time>
<must> 選修 </must>
<type> 講義 </type>
<place> 航太系館                      5821 </place>
<note></note>
</P4>

<P4 id="021">
<num>P4-021</num>
<class> 碩博                           </class>
<group></group>
<name> 微擾方法 </name>
<teacher> 王振源  </teacher>
<score> 3 </score>
<time day1="3" s1="3" e1="3" day2="4" s2="3" e2="4"> [3]3  ,  [4]3~4  </time>
<must> 選修 </must>
<type> 講義 </type>
<place> 航太系館                      5834 </place>
<note></note>
</P4>

<P4 id="022">
<num>P4-022</num>
<class> 碩博                           </class>
<group></group>
<name> 微機電製造 </name>
<teacher> 高　騏  </teacher>
<score> 3 </score>
<time day1="3" s1="6" e1="7" day2="4" s2="8" e2="8"> [3]6~7  ,  [4]8  </time>
<must> 選修 </must>
<type> 講義 </type>
<place> 航太系館                      5828 </place>
<note></note>
</P4>

<P4 id="023">
<num>P4-023</num>
<class> 碩博                           </class>
<group></group>
<name> 火箭推進 </name>
<teacher> 江滄柳  </teacher>
<score> 3 </score>
<time day1="2" s1="3" e1="4" day2="4" s2="3" e2="3"> [2]3~4  ,  [4]3  </time>
<must> 選修 </must>
<type> 講義 </type>
<place> 航太系館                      5833 </place>
<note></note>
</P4>

<P4 id="024">
<num>P4-024</num>
<class> 碩博                           </class>
<group></group>
<name> 數值熱傳 </name>
<teacher> 江滄柳  </teacher>
<score> 3 </score>
<time day1="4" s1="4" e1="4" day2="5" s2="3" e2="4"> [4]4  ,  [5]3~4  </time>
<must> 選修 </must>
<type> 講義 </type>
<place> 航太系館                      5833 </place>
<note></note>
</P4>

<P4 id="025">
<num>P4-025</num>
<class> 碩博                           </class>
<group></group>
<name> 燃燒理論（二） </name>
<teacher> 趙怡欽  </teacher>
<score> 3 </score>
<time day1="3" s1="6" e1="6" day2="2" s2="3" e2="4"> [3]6  ,  [2]3~4  </time>
<must> 選修 </must>
<type> 講義 </type>
<place> 航太系館                      5834 </place>
<note> 航太所與能源工程國際碩士博士學程合開 </note>
</P4>

<P4 id="026">
<num>P4-026</num>
<class> 碩博                           </class>
<group></group>
<name> 流場動態量測法 </name>
<teacher> 趙怡欽  </teacher>
<score> 3 </score>
<time day1="1" s1="6" e1="8"> [1]6~8  </time>
<must> 選修 </must>
<type> 講義 </type>
<place> 航太系館                      5821 </place>
<note></note>
</P4>

<P4 id="027">
<num>P4-027</num>
<class> 碩博                           </class>
<group></group>
<name> 物理氣體動力學 </name>
<teacher> 袁曉峰  </teacher>
<score> 3 </score>
<time day1="1" s1="6" e1="7" day2="2" s2="6" e2="6"> [1]6~7  ,  [2]6  </time>
<must> 選修 </must>
<type> 講義 </type>
<place> 航太系館                      5828 </place>
<note></note>
</P4>

<P4 id="028">
<num>P4-028</num>
<class> 碩博                           </class>
<group></group>
<name> 熱對流學 </name>
<teacher> 李定智  </teacher>
<score> 3 </score>
<time day1="2" s1="2" e1="2" day2="4" s2="3" e2="4"> [2]2  ,  [4]3~4  </time>
<must> 選修 </must>
<type> 講義 </type>
<place> 航太系館                      5828 </place>
<note></note>
</P4>

<P4 id="029">
<num>P4-029</num>
<class> 碩博                           </class>
<group></group>
<name> 熱輻射學 </name>
<teacher> 李約亨  </teacher>
<score> 3 </score>
<time day1="1" s1="3" e1="4" day2="3" s2="3" e2="3"> [1]3~4  ,  [3]3  </time>
<must> 選修 </must>
<type> 講義 </type>
<place> 航太系館                      5828 </place>
<note> 航太所與能源工程國際碩士博士學程合開 </note>
</P4>

<P4 id="042">
<num>P4-042</num>
<class> 碩博                           </class>
<group></group>
<name> 量子控制 </name>
<teacher> 楊憲東  </teacher>
<score> 3 </score>
<time day1="2" s1="3" e1="4" day2="3" s2="2" e2="2"> [2]3~4  ,  [3]2  </time>
<must> 選修 </must>
<type> 講義 </type>
<place> 航太系館                      5827 </place>
<note></note>
</P4>

<P4 id="043">
<num>P4-043</num>
<class> 碩博                           </class>
<group></group>
<name> 互動式學習理論與應用 </name>
<teacher> 譚俊豪  </teacher>
<score> 3 </score>
<time day1="1" s1="7" e1="9"> [1]7~9  </time>
<must> 選修 </must>
<type> 講義 </type>
<place> 航太系館                      5827 </place>
<note></note>
</P4>

<P4 id="045">
<num>P4-045</num>
<class> 碩博                           </class>
<group></group>
<name> 高等線性系統 </name>
<teacher> 譚俊豪  </teacher>
<score> 3 </score>
<time day1="4" s1="7" e1="9"> [4]7~9  </time>
<must> 選修 </must>
<type> 講義 </type>
<place> 航太系館                      5827 </place>
<note></note>
</P4>

<P4 id="046">
<num>P4-046</num>
<class> 碩博                           </class>
<group></group>
<name> 最佳控制原理 </name>
<teacher> 林穎裕  </teacher>
<score> 3 </score>
<time day1="2" s1="7" e1="8" day2="3" s2="8" e2="8"> [2]7~8  ,  [3]8  </time>
<must> 選修 </must>
<type> 講義 </type>
<place> 航太系館                      5836 </place>
<note></note>
</P4>

<P4 id="047">
<num>P4-047</num>
<class> 碩博                           </class>
<group></group>
<name> 飛具穩定控制 </name>
<teacher> 許棟龍  </teacher>
<score> 3 </score>
<time day1="2" s1="5" e1="6" day2="3" s2="5" e2="5"> [2]5~6  ,  [3]5  </time>
<must> 選修 </must>
<type> 講義 </type>
<place> 航太系館                      5829 </place>
<note></note>
</P4>

<P4 id="048">
<num>P4-048</num>
<class> 碩博                           </class>
<group></group>
<name> 高等動力學 </name>
<teacher> 林穎裕  </teacher>
<score> 3 </score>
<time day1="2" s1="6" e1="6" day2="4" s2="6" e2="7"> [2]6  ,  [4]6~7  </time>
<must> 選修 </must>
<type> 講義 </type>
<place> 航太系館                      5822 </place>
<note></note>
</P4>

<P4 id="049">
<num>P4-049</num>
<class> 碩博                           </class>
<group></group>
<name> 控制系統設計特論 </name>
<teacher> 陳介力  </teacher>
<score> 3 </score>
<time day1="3" s1="3" e1="3" day2="5" s2="3" e2="4"> [3]3  ,  [5]3~4  </time>
<must> 選修 </must>
<type> 講義 </type>
<place> 航太系館                      5822 </place>
<note> 航太所與能源國際工程碩士博士學程合開 </note>
</P4>

<P4 id="061">
<num>P4-061</num>
<class> 碩博                           </class>
<group></group>
<name> 計算流體力學（二） </name>
<teacher> 林三益  </teacher>
<score> 3 </score>
<time day1="1" s1="7" e1="8" day2="3" s2="8" e2="8"> [1]7~8  ,  [3]8  </time>
<must> 選修 </must>
<type> 講義 </type>
<place> 航太系館                      5834 </place>
<note></note>
</P4>

<P4 id="062">
<num>P4-062</num>
<class> 碩博                           </class>
<group></group>
<name> 紊流學 </name>
<teacher> 苗君易  </teacher>
<score> 3 </score>
<time day1="1" s1="1" e1="3"> [1]1~3  </time>
<must> 選修 </must>
<type> 講義 </type>
<place> 航太系館                      5821 </place>
<note></note>
</P4>

<P4 id="063">
<num>P4-063</num>
<class> 碩博                           </class>
<group></group>
<name> 數值分析 </name>
<teacher> 陳文立  </teacher>
<score> 3 </score>
<time day1="2" s1="6" e1="7" day2="4" s2="6" e2="6"> [2]6~7  ,  [4]6  </time>
<must> 選修 </must>
<type> 講義 </type>
<place> 航太系館                      5834 </place>
<note> 航太所與能源工程國際碩士博士學程合開 </note>
</P4>

<P4 id="064">
<num>P4-064</num>
<class> 碩博                           </class>
<group></group>
<name> 風能利用與風力發電 </name>
<teacher> 陳世雄  </teacher>
<score> 3 </score>
<time day1="3" s1="5" e1="7"> [3]5~7  </time>
<must> 選修 </must>
<type> 講義 </type>
<place> 航太系館                      5836 </place>
<note></note>
</P4>

<P4 id="065">
<num>P4-065</num>
<class> 碩博                           </class>
<group></group>
<name> 航空發動機設計 </name>
<teacher> 陳世雄  </teacher>
<score> 3 </score>
<time day1="1" s1="6" e1="8"> [1]6~8  </time>
<must> 選修 </must>
<type> 講義 </type>
<place> 航太系館                      5836 </place>
<note></note>
</P4>

<P4 id="066">
<num>P4-066</num>
<class> 碩博                           </class>
<group></group>
<name> 基因演算於工程最佳化之應用 </name>
<teacher> 潘大知  </teacher>
<score> 3 </score>
<time day1="2" s1="8" e1="8" day2="4" s2="7" e2="8"> [2]8  ,  [4]7~8  </time>
<must> 選修 </must>
<type> 講義 </type>
<place> 航太系館                      5821 </place>
<note></note>
</P4>

<P4 id="067">
<num>P4-067</num>
<class> 碩博                           </class>
<group></group>
<name> 氣體動力學 </name>
<teacher> 陳文立  </teacher>
<score> 3 </score>
<time day1="2" s1="4" e1="4" day2="4" s2="3" e2="4"> [2]4  ,  [4]3~4  </time>
<must> 選修 </must>
<type> 講義 </type>
<place> 航太系館                      5821 </place>
<note></note>
</P4>

<P4 id="068">
<num>P4-068</num>
<class> 碩博                           </class>
<group></group>
<name> 邊界層理論 </name>
<teacher> 呂宗行  </teacher>
<score> 3 </score>
<time day1="2" s1="3" e1="3" day2="4" s2="1" e2="2"> [2]3  ,  [4]1~2  </time>
<must> 選修 </must>
<type> 講義 </type>
<place> 航太系館                      5821 </place>
<note></note>
</P4>

<P4 id="069">
<num>P4-069</num>
<class> 碩博                           </class>
<group></group>
<name> 微流元件特論 </name>
<teacher> 葉思沂  </teacher>
<score> 3 </score>
<time day1="3" s1="2" e1="4"> [3]2~4  </time>
<must> 選修 </must>
<type> 講義 </type>
<place> 航太系館                      5833 </place>
<note></note>
</P4>

<P4 id="084">
<num>P4-084</num>
<class> 碩博                           </class>
<group></group>
<name> 高分子複材製造 </name>
<teacher> 楊文彬  </teacher>
<score> 3 </score>
<time day1="2" s1="3" e1="3" day2="4" s2="3" e2="4"> [2]3  ,  [4]3~4  </time>
<must> 選修 </must>
<type> 講義 </type>
<place> 航太系館                      5836 </place>
<note></note>
</P4>

<P4 id="085">
<num>P4-085</num>
<class> 碩博                           </class>
<group></group>
<name> 板殼理論 </name>
<teacher> 胡潛濱  </teacher>
<score> 3 </score>
<time day1="1" s1="6" e1="6" day2="3" s2="6" e2="7"> [1]6  ,  [3]6~7  </time>
<must> 選修 </must>
<type> 講義 </type>
<place> 航太系館                      5827 </place>
<note></note>
</P4>

<P4 id="086">
<num>P4-086</num>
<class> 碩博                           </class>
<group></group>
<name> 複合材料力學 </name>
<teacher> 鄭泗滄  </teacher>
<score> 3 </score>
<time day1="2" s1="6" e1="7" day2="3" s2="5" e2="5"> [2]6~7  ,  [3]5  </time>
<must> 選修 </must>
<type> 講義 </type>
<place> 航太系館                      5827 </place>
<note></note>
</P4>

<P4 id="301">
<num>P4-301</num>
<class> 碩專一                         </class>
<group></group>
<name> 專題討論（二） </name>
<teacher> 呂宗行  </teacher>
<score> 1 </score>
<time day1="5" s1="11" e1="12"> [5]B~C  </time>
<must> 必修 </must>
<type> 研討 </type>
<place> 航太系館                      5821 </place>
<note> 碩專一必修 </note>
</P4>

<P4 id="302">
<num>P4-302</num>
<class> 碩專二                         </class>
<group></group>
<name> 專題討論（四） </name>
<teacher> 呂宗行  </teacher>
<score> 1 </score>
<time day1="5" s1="11" e1="12"> [5]B~C  </time>
<must> 必修 </must>
<type> 研討 </type>
<place> 航太系館                      5821 </place>
<note> 碩專二必修 </note>
</P4>

<P4 id="303">
<num>P4-303</num>
<class> 碩專延三                       </class>
<group></group>
<name> 專題討論 </name>
<teacher> 呂宗行  </teacher>
<score> 0 </score>
<time day1="5" s1="11" e1="12"> [5]B~C  </time>
<must> 必修 </must>
<type> 研討 </type>
<place> 航太系館                      5821 </place>
<note> 僅供碩專班三以上必修 </note>
</P4>

<P4 id="310">
<num>P4-310</num>
<class> 碩專                           </class>
<group></group>
<name> 應用流體力學 </name>
<teacher> 林三益  </teacher>
<score> 3 </score>
<time day1="6" s1="2" e1="4"> [6]2~4  </time>
<must> 選修 </must>
<type> 講義 </type>
<place> 航太系館                      5821 </place>
<note></note>
</P4>

<P4 id="322">
<num>P4-322</num>
<class> 碩專                           </class>
<group></group>
<name> 熱學導論 </name>
<teacher> 張克勤  </teacher>
<score> 3 </score>
<time day1="6" s1="5" e1="7"> [6]5~7  </time>
<must> 選修 </must>
<type> 講義 </type>
<place> 航太系館                      5821 </place>
<note></note>
</P4>

<P4 id="323">
<num>P4-323</num>
<class> 碩專                           </class>
<group></group>
<name> 結構動力學 </name>
<teacher> 江達雲  </teacher>
<score> 3 </score>
<time day1="3" s1="10" e1="12"> [3]A~C  </time>
<must> 選修 </must>
<type> 講義 </type>
<place> 航太系館                      5821 </place>
<note></note>
</P4>

</content>
